Metadata-Version: 2.4
Name: ec3D
Version: 1.0.0
Summary: Reconstructing 3D structures of extrachromosomal DNA and other focal amplifications
Author: Biswanath Chowdhary
Author-email: Kaiyuan Zhu <kaiyuan-zhu@ucsd.edu>, Chaohui Li <chl221@ucsd.edu>
Maintainer-email: Kaiyuan Zhu <kaiyuan-zhu@ucsd.edu>, Chaohui Li <chl221@ucsd.edu>
License-Expression: BSD-3-Clause
Project-URL: Homepage, https://github.com/AmpliconSuite/ec3D
Project-URL: Repository, https://github.com/AmpliconSuite/ec3D
Classifier: Development Status :: 5 - Production/Stable
Classifier: Intended Audience :: Science/Research
Classifier: Operating System :: POSIX :: Linux
Classifier: Programming Language :: Python :: 3.8
Classifier: Programming Language :: Python :: 3.9
Classifier: Programming Language :: Python :: 3.10
Classifier: Programming Language :: Python :: 3.11
Classifier: Programming Language :: Python :: 3.12
Requires-Python: >=3.8
License-File: LICENSE
Requires-Dist: cooler>=0.10.2
Requires-Dist: iced>=0.5.10
Requires-Dist: scipy>=1.10.1
Requires-Dist: scikit-learn>=1.3.2
Requires-Dist: autograd>=1.6.2
Requires-Dist: networkx>=3.1
Requires-Dist: python-louvain>=0.16
Requires-Dist: plotly>=5.24.1
Requires-Dist: kaleido>=0.2.1
Requires-Dist: statsmodels>=0.14.5
Requires-Dist: matplotlib>=3.7.1
Requires-Dist: hic2cool>=0.8.3
Dynamic: license-file
